README.md
setup.cfg
setup.py
target_csv.py
target_csv.egg-info/PKG-INFO
target_csv.egg-info/SOURCES.txt
target_csv.egg-info/dependency_links.txt
target_csv.egg-info/entry_points.txt
target_csv.egg-info/requires.txt
target_csv.egg-info/top_level.txt